Workbook

Sheet Start Here
A1: Topic | B1: Instruction
A2: Purpose | B2: Feature-level manual acceptance tests. A feature is evaluated through successful workflow, important validation/failure handling and correctness/persistence—not each button.
A3: Scope | B3: 81 features; 239 acceptance cases. Eight simulator event families use a separate 46-template parameter matrix.
A4: Start | B4: Fill Run Setup. Prepare Test Data. Filter Test Cases by module/priority; execute and record actual outcome, evidence, tester, date and bug ID.
A5: Feature result | B5: Feature Coverage calculates Pass only when all required feature cases pass or have documented approved N/A, and all relevant event parameters pass. Failed/blocked/not-run checks prevent unconditional Pass.
A6: One-case discipline | B6: Complete all steps and expected criteria before Pass. If a grouped negative scenario contains several variants, record each actual variant; any mismatch fails the case. Use Retest Log for extra executions.
A7: Statuses | B7: Not Run: untouched. Pass: expected outcome observed. Fail: mismatch observed. Blocked: setup/dependency prevents execution. N/A: approved out-of-scope with reason; never use it to hide a failure.
A8: Evidence | B8: Use screenshot/output/export/QA object ID and source comparison. Do not include passwords, API keys, inventory bearer tokens or authenticator secrets.
A9: Safety | B9: Use isolated QA database/account/products/recommendations. Import replacement, retention, deletes, password changes and campaign publication have side effects; backup/restore and approved QA destination required.
A10: Priorities | B10: P0 core access/data integrity/simulation/integration; P1 feature workflows; P2 additional route/scope. Agree scope with QA lead and document unexecuted work.
A11: Acceptance | B11: All required cases and event variants passed with evidence; zero unresolved Critical/High defects unless explicitly accepted by lead. Test outcomes support functionality within tested scope, not every possible future condition.
A12: Snapshot | B12: 2026-10-15 merged working tree, HEAD b9a1e2d plus local desktop/inventory/diagnostic/simulator updates. Record actual installer hash/build; source line details are not the execution oracle.
A13: Previous pack | B13: Original per-click files moved to archive-per-click/. They are superseded and are not part of this feature-level run.

Sheet Run Setup
A1: Field | B1: Value
A2: Run ID
A3: QA date
A4: QA lead / testers
A5: Build / commit / local changes
A6: Installer filename / SHA256
A7: OS / architecture / browser
A8: Viewport / zoom
A9: QA environment / DB snapshot
A10: QA data versions
A11: Timezone / target date
A12: Agreed included features
A13: Approved N/A / limitations
... A15: Final sign-off

Sheet Feature Coverage
A1: Feature ID | B1: Module | C1: Feature | D1: Acceptance Goal | E1: Test IDs | F1: Feature Result | G1: Scope / N-A Reason
A2: F-001 | B2: Login & Recovery | C2: Owner login and MFA | D2: Only authorized owner with required MFA can access the system. | E2: TC-001, TC-002, TC-003 | F2: =IF(COUNTIFS('Test Cases'!$B$2:$B$240,A2,'Test Cases'!$M$2:$M$240,"Fail")+COUNTIFS('Event Parameters'!$B$2:$B$47,A2,'Event Parameters'!$J$2:$J$47,"Fail")>0,"Fail",IF(COUNTIFS('Test Cases'!$B$2:$B$240,A2,'Test Cases'!$M$2:$M$240,"Blocked")+COUNTIFS('Event Parameters'!$B$2:$B$47,A2,'Event Parameters'!$J$2:$J$47,"Blocked")>0,"Blocked",IF(COUNTIFS('Test Cases'!$B$2:$B$240,A2,'Test Cases'!$M$2:$M$240,"Not Run")+COUNTIFS('Event Parameters'!$B$2:$B$47,A2,'Event Parameters'!$J$2:$J$47,"Not Run")>0,"Not Run",IF(COUNTIFS('Test Cases'!$B$2:$B$240,A2,'Test Cases'!$M$2:$M$240,"Pass")+COUNTIFS('Event Parameters'!$B$2:$B$47,A2,'Event Parameters'!$J$2:$J$47,"Pass")>0,"Pass","N/A"))))
A3: F-002 | B3: Login & Recovery | C3: Password recovery | D3: Recover account through valid secure email link. | E3: TC-004, TC-005, TC-006 | F3: =IF(COUNTIFS('Test Cases'!$B$2:$B$240,A3,'Test Cases'!$M$2:$M$240,"Fail")+COUNTIFS('Event Parameters'!$B$2:$B$47,A3,'Event Parameters'!$J$2:$J$47,"Fail")>0,"Fail",IF(COUNTIFS('Test Cases'!$B$2:$B$240,A3,'Test Cases'!$M$2:$M$240,"Blocked")+COUNTIFS('Event Parameters'!$B$2:$B$47,A3,'Event Parameters'!$J$2:$J$47,"Blocked")>0,"Blocked",IF(COUNTIFS('Test Cases'!$B$2:$B$240,A3,'Test Cases'!$M$2:$M$240,"Not Run")+COUNTIFS('Event Parameters'!$B$2:$B$47,A3,'Event Parameters'!$J$2:$J$47,"Not Run")>0,"Not Run",IF(COUNTIFS('Test Cases'!$B$2:$B$240,A3,'Test Cases'!$M$2:$M$240,"Pass")+COUNTIFS('Event Parameters'!$B$2:$B$47,A3,'Event Parameters'!$J$2:$J$47,"Pass")>0,"Pass","N/A"))))
A4: F-003 | B4: Login & Recovery | C4: Authenticator enrollment | D4: Enroll and verify MFA only through authorized setup. | E4: TC-007, TC-008, TC-009 | F4: =IF(COUNTIFS('Test Cases'!$B$2:$B$240,A4,'Test Cases'!$M$2:$M$240,"Fail")+COUNTIFS('Event Parameters'!$B$2:$B$47,A4,'Event Parameters'!$J$2:$J$47,"Fail")>0,"Fail",IF(COUNTIFS('Test Cases'!$B$2:$B$240,A4,'Test Cases'!$M$2:$M$240,"Blocked")+COUNTIFS('Event Parameters'!$B$2:$B$47,A4,'Event Parameters'!$J$2:$J$47,"Blocked")>0,"Blocked",IF(COUNTIFS('Test Cases'!$B$2:$B$240,A4,'Test Cases'!$M$2:$M$240,"Not Run")+COUNTIFS('Event Parameters'!$B$2:$B$47,A4,'Event Parameters'!$J$2:$J$47,"Not Run")>0,"Not Run",IF(COUNTIFS('Test Cases'!$B$2:$B$240,A4,'Test Cases'!$M$2:$M$240,"Pass")+COUNTIFS('Event Parameters'!$B$2:$B$47,A4,'Event Parameters'!$J$2:$J$47,"Pass")>0,"Pass","N/A"))))
A5: F-004 | B5: Navigation & Header | C5: Sign-out and session timeout | D5: End access reliably on logout or true inactivity. | E5: TC-010, TC-011, TC-012 | F5: =IF(COUNTIFS('Test Cases'!$B$2:$B$240,A5,'Test Cases'!$M$2:$M$240,"Fail")+COUNTIFS('Event Parameters'!$B$2:$B$47,A5,'Event Parameters'!$J$2:$J$47,"Fail")>0,"Fail",IF(COUNTIFS('Test Cases'!$B$2:$B$240,A5,'Test Cases'!$M$2:$M$240,"Blocked")+COUNTIFS('Event Parameters'!$B$2:$B$47,A5,'Event Parameters'!$J$2:$J$47,"Blocked")>0,"Blocked",IF(COUNTIFS('Test Cases'!$B$2:$B$240,A5,'Test Cases'!$M$2:$M$240,"Not Run")+COUNTIFS('Event Parameters'!$B$2:$B$47,A5,'Event Parameters'!$J$2:$J$47,"Not Run")>0,"Not Run",IF(COUNTIFS('Test Cases'!$B$2:$B$240,A5,'Test Cases'!$M$2:$M$240,"Pass")+COUNTIFS('Event Parameters'!$B$2:$B$47,A5,'Event Parameters'!$J$2:$J$47,"Pass")>0,"Pass","N/A"))))
A6: F-005 | B6: Navigation & Header | C6: Page navigation and responsive sidebar | D6: Reach all main modules with consistent selected route. | E6: TC-013, TC-014, TC-015 | F6: =IF(COUNTIFS('Test Cases'!$B$2:$B$240,A6,'Test Cases'!$M$2:$M$240,"Fail")+COUNTIFS('Event Parameters'!$B$2:$B$47,A6,'Event Parameters'!$J$2:$J$47,"Fail")>0,"Fail",IF(COUNTIFS('Test Cases'!$B$2:$B$240,A6,'Test Cases'!$M$2:$M$240,"Blocked")+COUNTIFS('Event Parameters'!$B$2:$B$47,A6,'Event Parameters'!$J$2:$J$47,"Blocked")>0,"Blocked",IF(COUNTIFS('Test Cases'!$B$2:$B$240,A6,'Test Cases'!$M$2:$M$240,"Not Run")+COUNTIFS('Event Parameters'!$B$2:$B$47,A6,'Event Parameters'!$J$2:$J$47,"Not Run")>0,"Not Run",IF(COUNTIFS('Test Cases'!$B$2:$B$240,A6,'Test Cases'!$M$2:$M$240,"Pass")+COUNTIFS('Event Parameters'!$B$2:$B$47,A6,'Event Parameters'!$J$2:$J$47,"Pass")>0,"Pass","N/A"))))
A7: F-006 | B7: Navigation & Header | C7: Global reporting date scope | D7: Apply correct shared reporting date range. | E7: TC-016, TC-017, TC-018 | F7: =IF(COUNTIFS('Test Cases'!$B$2:$B$240,A7,'Test Cases'!$M$2:$M$240,"Fail")+COUNTIFS('Event Parameters'!$B$2:$B$47,A7,'Event Parameters'!$J$2:$J$47,"Fail")>0,"Fail",IF(COUNTIFS('Test Cases'!$B$2:$B$240,A7,'Test Cases'!$M$2:$M$240,"Blocked")+COUNTIFS('Event Parameters'!$B$2:$B$47,A7,'Event Parameters'!$J$2:$J$47,"Blocked")>0,"Blocked",IF(COUNTIFS('Test Cases'!$B$2:$B$240,A7,'Test Cases'!$M$2:$M$240,"Not Run")+COUNTIFS('Event Parameters'!$B$2:$B$47,A7,'Event Parameters'!$J$2:$J$47,"Not Run")>0,"Not Run",IF(COUNTIFS('Test Cases'!$B$2:$B$240,A7,'Test Cases'!$M$2:$M$240,"Pass")+COUNTIFS('Event Parameters'!$B$2:$B$47,A7,'Event Parameters'!$J$2:$J$47,"Pass")>0,"Pass","N/A"))))
A8: F-007 | B8: Navigation & Header | C8: Notification management | D8: View, filter, act on and dismiss real notifications. | E8: TC-019, TC-020, TC-021 | F8: =IF(COUNTIFS('Test Cases'!$B$2:$B$240,A8,'Test Cases'!$M$2:$M$240,"Fail")+COUNTIFS('Event Parameters'!$B$2:$B$47,A8,'Event Parameters'!$J$2:$J$47,"Fail")>0,"Fail",IF(COUNTIFS('Test Cases'!$B$2:$B$240,A8,'Test Cases'!$M$2:$M$240,"Blocked")+COUNTIFS('Event Parameters'!$B$2:$B$47,A8,'Event Parameters'!$J$2:$J$47,"Blocked")>0,"Blocked",IF(COUNTIFS('Test Cases'!$B$2:$B$240,A8,'Test Cases'!$M$2:$M$240,"Not Run")+COUNTIFS('Event Parameters'!$B$2:$B$47,A8,'Event Parameters'!$J$2:$J$47,"Not Run")>0,"Not Run",IF(COUNTIFS('Test Cases'!$B$2:$B$240,A8,'Test Cases'!$M$2:$M$240,"Pass")+COUNTIFS('Event Parameters'!$B$2:$B$47,A8,'Event Parameters'!$J$2:$J$47,"Pass")>0,"Pass","N/A"))))
A9: F-008 | B9: Home | C9: Priority alerts and snoozing | D9: Present actionable business alerts with traceable acknowledgment. | E9: TC-022, TC-023, TC-024 | F9: =IF(COUNTIFS('Test Cases'!$B$2:$B$240,A9,'Test Cases'!$M$2:$M$240,"Fail")+COUNTIFS('Event Parameters'!$B$2:$B$47,A9,'Event Parameters'!$J$2:$J$47,"Fail")>0,"Fail",IF(COUNTIFS('Test Cases'!$B$2:$B$240,A9,'Test Cases'!$M$2:$M$240,"Blocked")+COUNTIFS('Event Parameters'!$B$2:$B$47,A9,'Event Parameters'!$J$2:$J$47,"Blocked")>0,"Blocked",IF(COUNTIFS('Test Cases'!$B$2:$B$240,A9,'Test Cases'!$M$2:$M$240,"Not Run")+COUNTIFS('Event Parameters'!$B$2:$B$47,A9,'Event Parameters'!$J$2:$J$47,"Not Run")>0,"Not Run",IF(COUNTIFS('Test Cases'!$B$2:$B$240,A9,'Test Cases'!$M$2:$M$240,"Pass")+COUNTIFS('Event Parameters'!$B$2:$B$47,A9,'Event Parameters'!$J$2:$J$47,"Pass")>0,"Pass","N/A"))))
A10: F-009 | B10: Data Ingestion | C10: Transaction import and ETL | D10: Import supported exports into correct channels/sectors. | E10: TC-025, TC-026, TC-027 | F10: =IF(COUNTIFS('Test Cases'!$B$2:$B$240,A10,'Test Cases'!$M$2:$M$240,"Fail")+COUNTIFS('Event Parameters'!$B$2:$B$47,A10,'Event Parameters'!$J$2:$J$47,"Fail")>0,"Fail",IF(COUNTIFS('Test Cases'!$B$2:$B$240,A10,'Test Cases'!$M$2:$M$240,"Blocked")+COUNTIFS('Event Parameters'!$B$2:$B$47,A10,'Event Parameters'!$J$2:$J$47,"Blocked")>0,"Blocked",IF(COUNTIFS('Test Cases'!$B$2:$B$240,A10,'Test Cases'!$M$2:$M$240,"Not Run")+COUNTIFS('Event Parameters'!$B$2:$B$47,A10,'Event Parameters'!$J$2:$J$47,"Not Run")>0,"Not Run",IF(COUNTIFS('Test Cases'!$B$2:$B$240,A10,'Test Cases'!$M$2:$M$240,"Pass")+COUNTIFS('Event Parameters'!$B$2:$B$47,A10,'Event Parameters'!$J$2:$J$47,"Pass")>0,"Pass","N/A"))))
A11: F-010 | B11: Data Ingestion | C11: Import replacement and deletion | D11: Maintain intended upload lifecycle without unrelated data loss. | E11: TC-028, TC-029, TC-030 | F11: =IF(COUNTIFS('Test Cases'!$B$2:$B$240,A11,'Test Cases'!$M$2:$M$240,"Fail")+COUNTIFS('Event Parameters'!$B$2:$B$47,A11,'Event Parameters'!$J$2:$J$47,"Fail")>0,"Fail",IF(COUNTIFS('Test Cases'!$B$2:$B$240,A11,'Test Cases'!$M$2:$M$240,"Blocked")+COUNTIFS('Event Parameters'!$B$2:$B$47,A11,'Event Parameters'!$J$2:$J$47,"Blocked")>0,"Blocked",IF(COUNTIFS('Test Cases'!$B$2:$B$240,A11,'Test Cases'!$M$2:$M$240,"Not Run")+COUNTIFS('Event Parameters'!$B$2:$B$47,A11,'Event Parameters'!$J$2:$J$47,"Not Run")>0,"Not Run",IF(COUNTIFS('Test Cases'!$B$2:$B$240,A11,'Test Cases'!$M$2:$M$240,"Pass")+COUNTIFS('Event Parameters'!$B$2:$B$47,A11,'Event Parameters'!$J$2:$J$47,"Pass")>0,"Pass","N/A"))))
A12: F-011 | B12: Data Ingestion | C12: PetHub transaction-ingestion exclusion | D12: Keep PetHub transactions blocked while inventory remains separate. | E12: TC-031, TC-032, TC-033 | F12: =IF(COUNTIFS('Test Cases'!$B$2:$B$240,A12,'Test Cases'!$M$2:$M$240,"Fail")+COUNTIFS('Event Parameters'!$B$2:$B$47,A12,'Event Parameters'!$J$2:$J$47,"Fail")>0,"Fail",IF(COUNTIFS('Test Cases'!$B$2:$B$240,A12,'Test Cases'!$M$2:$M$240,"Blocked")+COUNTIFS('Event Parameters'!$B$2:$B$47,A12,'Event Parameters'!$J$2:$J$47,"Blocked")>0,"Blocked",IF(COUNTIFS('Test Cases'!$B$2:$B$240,A12,'Test Cases'!$M$2:$M$240,"Not Run")+COUNTIFS('Event Parameters'!$B$2:$B$47,A12,'Event Parameters'!$J$2:$J$47,"Not Run")>0,"Not Run",IF(COUNTIFS('Test Cases'!$B$2:$B$240,A12,'Test Cases'!$M$2:$M$240,"Pass")+COUNTIFS('Event Parameters'!$B$2:$B$47,A12,'Event Parameters'!$J$2:$J$47,"Pass")>0,"Pass","N/A"))))
A13: F-012 | B13: Home | C13: Omnichannel KPI analytics | D13: Report accurate total revenue, orders and AOV. | E13: TC-034, TC-035, TC-036 | F13: =IF(COUNTIFS('Test Cases'!$B$2:$B$240,A13,'Test Cases'!$M$2:$M$240,"Fail")+COUNTIFS('Event Parameters'!$B$2:$B$47,A13,'Event Parameters'!$J$2:$J$47,"Fail")>0,"Fail",IF(COUNTIFS('Test Cases'!$B$2:$B$240,A13,'Test Cases'!$M$2:$M$240,"Blocked")+COUNTIFS('Event Parameters'!$B$2:$B$47,A13,'Event Parameters'!$J$2:$J$47,"Blocked")>0,"Blocked",IF(COUNTIFS('Test Cases'!$B$2:$B$240,A13,'Test Cases'!$M$2:$M$240,"Not Run")+COUNTIFS('Event Parameters'!$B$2:$B$47,A13,'Event Parameters'!$J$2:$J$47,"Not Run")>0,"Not Run",IF(COUNTIFS('Test Cases'!$B$2:$B$240,A13,'Test Cases'!$M$2:$M$240,"Pass")+COUNTIFS('Event Parameters'!$B$2:$B$47,A13,'Event Parameters'!$J$2:$J$47,"Pass")>0,"Pass","N/A"))))
... A82: F-081 | B82: End-to-end | C82: Cross-module business workflows | D82: Verify integrated features work together with one consistent record/data context. | E82: TC-233, TC-234, TC-235, TC-236, TC-237, TC-238, TC-239 | F82: =IF(COUNTIFS('Test Cases'!$B$2:$B$240,A82,'Test Cases'!$M$2:$M$240,"Fail")+COUNTIFS('Event Parameters'!$B$2:$B$47,A82,'Event Parameters'!$J$2:$J$47,"Fail")>0,"Fail",IF(COUNTIFS('Test Cases'!$B$2:$B$240,A82,'Test Cases'!$M$2:$M$240,"Blocked")+COUNTIFS('Event Parameters'!$B$2:$B$47,A82,'Event Parameters'!$J$2:$J$47,"Blocked")>0,"Blocked",IF(COUNTIFS('Test Cases'!$B$2:$B$240,A82,'Test Cases'!$M$2:$M$240,"Not Run")+COUNTIFS('Event Parameters'!$B$2:$B$47,A82,'Event Parameters'!$J$2:$J$47,"Not Run")>0,"Not Run",IF(COUNTIFS('Test Cases'!$B$2:$B$240,A82,'Test Cases'!$M$2:$M$240,"Pass")+COUNTIFS('Event Parameters'!$B$2:$B$47,A82,'Event Parameters'!$J$2:$J$47,"Pass")>0,"Pass","N/A"))))

Sheet Test Cases
A1: Test ID | B1: Feature ID | C1: Module | D1: Feature | E1: Scenario | F1: Priority | G1: Preconditions | H1: Test Data | I1: Steps | J1: Expected Result | K1: Cleanup / Safety | L1: Source | M1: Status | N1: Actual Result | O1: Bug ID | P1: Tester | Q1: Executed At | R1: Evidence
A2: TC-001 | B2: F-001 | C2: Login & Recovery | D2: Owner login and MFA | E2: Successful workflow | F2: P0 | G2: Use approved QA environment, required fixtures and authorized QA account; open the feature location. For access tests begin in stated signed-out state. | H2: QA-AUTH | I2: Start signed out. Enter valid QA owner credentials; complete current authenticator challenge; access Home and protected analytics. | J2: Login completes with required MFA; correct owner context and protected data are available. | K2: QA accounts only; do not record credentials or authenticator codes. | L2: frontend/src/app/pages/Login.tsx | M2: Not Run
A3: TC-002 | B3: F-001 | C3: Login & Recovery | D3: Owner login and MFA | E3: Validation / failure handling | F3: P0 | G3: Use approved QA environment, required fixtures and authorized QA account; open the feature location. For access tests begin in stated signed-out state. | H3: QA-AUTH | I3: Try blank/malformed inputs, invalid credentials, unauthorized account and invalid/expired MFA in separate attempts. | J3: All invalid attempts remain denied with meaningful non-enumerating feedback; no protected data or session is exposed. | K3: QA accounts only; do not record credentials or authenticator codes. | L3: frontend/src/app/pages/Login.tsx | M3: Not Run
A4: TC-003 | B4: F-001 | C4: Login & Recovery | D4: Owner login and MFA | E4: Correctness / persistence | F4: P0 | G4: Use approved QA environment, required fixtures and authorized QA account; open the feature location. For access tests begin in stated signed-out state. | H4: QA-AUTH | I4: With no session open protected routes/API; then authenticate, reload and revisit /login. | J4: Unauthorized access is blocked; valid session survives supported navigation/reload; authenticated login route redirects correctly. | K4: QA accounts only; do not record credentials or authenticator codes. | L4: frontend/src/app/pages/Login.tsx | M4: Not Run
A5: TC-004 | B5: F-002 | C5: Login & Recovery | D5: Password recovery | E5: Successful workflow | F5: P1 | G5: Use approved QA environment, required fixtures and authorized QA account; open the feature location. For access tests begin in stated signed-out state. | H5: QA-AUTH | I5: Request reset for QA inbox; open fresh emailed link in supported website; set matching compliant password; sign in. | J5: Secure recovery completes; new password works with required MFA; old password no longer works. | K5: Use dedicated QA account/inbox; restore QA access afterward. | L5: frontend/src/app/pages/Login.tsx | M5: Not Run
A6: TC-005 | B6: F-002 | C6: Login & Recovery | D6: Password recovery | E6: Validation / failure handling | F6: P1 | G6: Use approved QA environment, required fixtures and authorized QA account; open the feature location. For access tests begin in stated signed-out state. | H6: QA-AUTH | I6: Try unknown email, expired/reused link, short password and mismatching confirmation separately. | J6: Unknown account response is neutral; invalid link/password attempts cannot change password. | K6: Use dedicated QA account/inbox; restore QA access afterward. | L6: frontend/src/app/pages/Login.tsx | M6: Not Run
A7: TC-006 | B7: F-002 | C7: Login & Recovery | D7: Password recovery | E7: Correctness / persistence | F7: P1 | G7: Use approved QA environment, required fixtures and authorized QA account; open the feature location. For access tests begin in stated signed-out state. | H7: QA-AUTH | I7: Cancel recovery request before sending; verify account unchanged. Inspect successful recovery session/redirect and log out. | J7: Cancel has no side effect; recovery links/session are scoped to intended account; secrets are not returned in messages. | K7: Use dedicated QA account/inbox; restore QA access afterward. | L7: frontend/src/app/pages/Login.tsx | M7: Not Run
A8: TC-007 | B8: F-003 | C8: Login & Recovery | D8: Authenticator enrollment | E8: Successful workflow | F8: P1 | G8: Use approved QA environment, required fixtures and authorized QA account; open the feature location. For access tests begin in stated signed-out state. | H8: QA-AUTH | I8: In enabled QA website, authenticate an unenrolled QA account; scan enrollment QR/manual secret; submit current code. | J8: Factor verifies and session meets required assurance; protected dashboard becomes available. | K8: Dedicated unenrolled test account only; never screenshot QR/manual secret. | L8: frontend/src/app/pages/Login.tsx | M8: Not Run
A9: TC-008 | B9: F-003 | C9: Login & Recovery | D9: Authenticator enrollment | E9: Validation / failure handling | F9: P1 | G9: Use approved QA environment, required fixtures and authorized QA account; open the feature location. For access tests begin in stated signed-out state. | H9: QA-AUTH | I9: Try invalid code and unauthorized/disabled enrollment environment. | J9: No false enrollment, factor mutation or access grant; clear blocked/disabled state. | K9: Dedicated unenrolled test account only; never screenshot QR/manual secret. | L9: frontend/src/app/pages/Login.tsx | M9: Not Run
A10: TC-009 | B10: F-003 | C10: Login & Recovery | D10: Authenticator enrollment | E10: Correctness / persistence | F10: P1 | G10: Use approved QA environment, required fixtures and authorized QA account; open the feature location. For access tests begin in stated signed-out state. | H10: QA-AUTH | I10: After enrollment sign out and back in; inspect current desktop enrollment behavior separately. | J10: New logins require enrolled factor; desktop guidance is truthful. Full desktop enrollment is not considered implemented by a guidance page. | K10: Dedicated unenrolled test account only; never screenshot QR/manual secret. | L10: frontend/src/app/pages/Login.tsx | M10: Not Run
A11: TC-010 | B11: F-004 | C11: Navigation & Header | D11: Sign-out and session timeout | E11: Successful workflow | F11: P0 | G11: Use approved QA environment, required fixtures and authorized QA account; open the feature location. For access tests begin in stated signed-out state. | H11: QA-BASE | I11: Sign in, open profile and sign out; attempt Back, reload and protected route access. | J11: Server session is cleared; protected data cannot be reused. | K11: Restore original timeout; use QA account. | L11: frontend/src/app/components/Header.tsx | M11: Not Run
A12: TC-011 | B12: F-004 | C12: Navigation & Header | D12: Sign-out and session timeout | E12: Validation / failure handling | F12: P0 | G12: Use approved QA environment, required fixtures and authorized QA account; open the feature location. For access tests begin in stated signed-out state. | H12: QA-BASE | I12: Set shortest supported QA timeout; wait idle. In separate run interact before expiry. | J12: Idle session expires safely; valid activity resets timer; no bypass through browser history. | K12: Restore original timeout; use QA account. | L12: frontend/src/app/components/Header.tsx | M12: Not Run
A13: TC-012 | B13: F-004 | C13: Navigation & Header | D13: Sign-out and session timeout | E13: Correctness / persistence | F13: P0 | G13: Use approved QA environment, required fixtures and authorized QA account; open the feature location. For access tests begin in stated signed-out state. | H13: QA-BASE | I13: Relaunch desktop/browser after logout; inspect session state and login requirement. | J13: No protected stale screen remains usable; logout is consistent across main features. | K13: Restore original timeout; use QA account. | L13: frontend/src/app/components/Header.tsx | M13: Not Run
... A240: TC-239 | B240: F-081 | C240: End-to-end | D240: Cross-module business workflows | E240: Owner secure access | F240: P0 | G240: Use approved QA environment, required fixtures and authorized QA account; open the feature location. For access tests begin in stated signed-out state. | H240: Relevant QA fixtures | I240: 1. Sign in QA owner using valid MFA. 2. Access analytics, inventory and saved runs. 3. Sign out. 4. Use back/reload/direct protected paths. | J240: Protected access requires valid authorized MFA session; sign-out prevents reuse of protected UI/API. | K240: QA environment only; remove created records and restore baseline. | L240: Multiple modules; see scope guide | M240: Not Run

Sheet Event Parameters
A1: Parameter ID | B1: Feature ID | C1: Family | D1: Template | E1: Sector | F1: Effect | G1: Default Value | H1: Duration min | I1: Setup | J1: Status | K1: Actual / Engine Evidence | L1: Saved Run ID | M1: Tester / Date | N1: Bug ID
A2: EP-01 | B2: F-045 | C2: Staff availability | D2: Relief cafe staff arrives | E2: Cafe | F2: staff | G2: 1 | H2: 120 | I2: Independent QA run; seed12345; inject at t120; eligible future workload/resources. | J2: Not Run
A3: EP-02 | B3: F-045 | C3: Staff availability | D3: Cafe staff meal break | E3: Cafe | F3: staff | G3: -1 | H3: 30 | I3: Independent QA run; seed12345; inject at t120; eligible future workload/resources. | J3: Not Run
A4: EP-03 | B4: F-046 | C4: Stations and equipment | D4: Backup grooming station opened | E4: Services | F4: stations | G4: 1 | H4: 120 | I4: Independent QA run; seed12345; inject at t120; eligible future workload/resources. | J4: Not Run
A5: EP-04 | B5: F-046 | C5: Stations and equipment | D5: Cafe preparation station malfunction | E5: Cafe | F5: stations | G5: -1 | H5: 45 | I5: Independent QA run; seed12345; inject at t120; eligible future workload/resources. | J5: Not Run
A6: EP-05 | B6: F-046 | C6: Stations and equipment | D6: Backup cafe preparation station opened | E6: Cafe | F6: stations | G6: 1 | H6: 120 | I6: Independent QA run; seed12345; inject at t120; eligible future workload/resources. | J6: Not Run
A7: EP-06 | B7: F-047 | C7: Facility closures | D7: Cafe sanitation pause | E7: Cafe | F7: closure | G7: 1 | H7: 15 | I7: Independent QA run; seed12345; inject at t120; eligible future workload/resources. | J7: Not Run
A8: EP-07 | B8: F-047 | C8: Facility closures | D8: Grooming area deep cleaning | E8: Services | F8: closure | G8: 1 | H8: 20 | I8: Independent QA run; seed12345; inject at t120; eligible future workload/resources. | J8: Not Run
A9: EP-08 | B9: F-048 | C9: Inventory supply disruption/restock | D9: Grooming consumables damaged (20 units) | E9: Services | F9: inventory | G9: -20 | H9: 1 | I9: Independent QA run; seed12345; inject at t120; eligible future workload/resources. | J9: Not Run
A10: EP-09 | B10: F-048 | C10: Inventory supply disruption/restock | D10: Cafe ingredient spoilage (20 units) | E10: Cafe | F10: inventory | G10: -20 | H10: 1 | I10: Independent QA run; seed12345; inject at t120; eligible future workload/resources. | J10: Not Run
A11: EP-10 | B11: F-049 | C11: Checkout and payment | D11: Express checkout process enabled | E11: All | F11: checkout | G11: 0.5 | H11: 60 | I11: Independent QA run; seed12345; inject at t120; eligible future workload/resources. | J11: Not Run
A12: EP-11 | B12: F-049 | C12: Checkout and payment | D12: Manual payment verification required | E12: All | F12: checkout | G12: 2 | H12: 45 | I12: Independent QA run; seed12345; inject at t120; eligible future workload/resources. | J12: Not Run
A13: EP-12 | B13: F-050 | C13: Demand surge or reduction | D13: Nearby event increases customer arrivals | E13: All | F13: demand | G13: 1.4 | H13: 90 | I13: Independent QA run; seed12345; inject at t120; eligible future workload/resources. | J13: Not Run
... A47: EP-46 | B47: F-047 | C47: Facility closures | D47: Fire alarm / evacuation / power outage | E47: All | F47: closure | G47: 1 | H47: 30 | I47: Independent QA run; seed12345; inject at t120; eligible future workload/resources. | J47: Not Run

Sheet Test Data
A1: Data ID | B1: Fixture / Setup | C1: Oracle / Cleanup
A2: QA-BASE | B2: Authorized QA owner, known datasets, backend and required providers available | C2: Record environment/build and restore baseline between state-changing cases. Never paste passwords/tokens into workbook.
A3: QA-AUTH | B3: Enrolled QA owner, unknown email, unauthorized QA user, disposable unenrolled QA account and QA inbox | C3: Keep credentials in approved secret store. Password/MFA mutations only dedicated test accounts.
A4: QA-UPLOAD | B4: Approved POS CSV/Excel, Shopee and TikTok export copies; PetHub blocked-input fixture; duplicate, malformed, empty and size-boundary variants | C4: Use real accepted vendor schema; ledger file is NOT an uploader template. Record raw row count, rejected count and accepted totals before running.
A5: QA-LEDGER | B5: QA_REFERENCE_LEDGER.csv; normalized reference rows, 2026-09-30 vs 2026-10-01 | C5: Map through supported test import/seed mechanism in isolated DB. Expected: prior 900; current gross1320, discounts110, net1210; 5 distinct transactions; 9 units; AOV242; Cafe320/2orders/5units; Services450/1order/1unit; Retail440/2orders/3units; totaldelta310 (34.444...%).
A6: QA-FORECAST | B6: Date with known traffic/hourly forecast plus production/holdout/fixed-window outputs | C6: Save actual API payload, date/hour range and sector counts as oracle. Forecast totals are not unique-person counts unless explicitly supported.
A7: QA-SIM | B7: Custom scenario: date2026-10-15, open08:00, duration600min, seed12345; Services3staff/3stations, Cafe2staff/2stations, cashier1; enough supply/demand; random events OFF for controlled comparisons | C7: Record effective exported config. Use 120 customers for event workload or a smaller run for lifecycle. Effects may be zero when no eligible future customers; create targeted demand fixture instead of inventing expected impact.
A8: QA-INVENTORY | B8: QA Pet Shop products: active stock12, active stock0, active stocknull, inactive stock7; nullSKU/threshold; >200 products for pagination; one disposable removal | C8: Record real UUIDs from QA source; no fake fixed UUIDs required. Restore stock/active/category/deletion test fixtures after run. Source response/API is quantity oracle.
A9: QA-BUNDLES | B9: Receipts with known co-purchase pair; enough support; distinct catalog products; QA-prefixed manual bundles | C9: Hand-calculate support=count(A&B)/receipts; confidence=count(A&B)/count(A); lift=confidence/support(B); empty-support fixture too.
A10: QA-CAMPAIGN | B10: Disposable recommendation and authorized QA publish destination | C10: Publishing is external side effect. If no approved QA target, mark publication cases Blocked; do not publish to production.
A11: QA-REPORT | B11: Known-window data, unique QA title, existing and generated disposable reports; no-data and partial-data windows | C11: Include 30-day boundary and >30-day window. Retain exports for verification; clean created reports afterward.
A12: QA-FEEDBACK | B12: Separate fresh active recommendations for helpful, unhelpful and end-promotion cases | C12: Feedback changes model inputs; use isolated data and avoid recycling same record for incompatible paths.
... A16: QA-ALERTS | B16: Known eligible QA notifications, capacity/quiet-period alerts and threshold scenarios | C16: Record alert IDs, source rule/threshold/date and expected eligibility; use disposable records; restore thresholds and snooze state.

Sheet Reference Ledger
A1: Business date | B1: Transaction ID | C1: Sector | D1: Channel | E1: Reference SKU | F1: Product | G1: Qty | H1: Unit Price | I1: Discount | J1: Expected Net
A2: 2026-09-30 | B2: PC001 | C2: Cafe | D2: POS | E2: LATTE-QA | F2: QA Latte | G2: 3 | H2: 100 | I2: 0 | J2: 300
A3: 2026-09-30 | B3: PS001 | C3: Services | D3: POS | E3: GROOM-QA | F3: QA Grooming | G3: 1 | H3: 400 | I3: 0 | J3: 400
A4: 2026-09-30 | B4: PR001 | C4: Retail | D4: POS | E4: FOOD-QA | F4: QA Pet Food | G4: 1 | H4: 200 | I4: 0 | J4: 200
A5: 2026-10-01 | B5: C001 | C5: Cafe | D5: POS | E5: LATTE-QA | F5: QA Latte | G5: 2 | H5: 100 | I5: 20 | J5: 180
A6: 2026-10-01 | B6: C001 | C6: Cafe | D6: POS | E6: MUFFIN-QA | F6: QA Muffin | G6: 1 | H6: 60 | I6: 0 | J6: 60
A7: 2026-10-01 | B7: C002 | C7: Cafe | D7: POS | E7: COOKIE-QA | F7: QA Pet Cookie | G7: 2 | H7: 40 | I7: 0 | J7: 80
A8: 2026-10-01 | B8: S001 | C8: Services | D8: POS | E8: GROOM-QA | F8: QA Grooming | G8: 1 | H8: 500 | I8: 50 | J8: 450
A9: 2026-10-01 | B9: R001 | C9: Retail | D9: POS | E9: FOOD-QA | F9: QA Pet Food | G9: 2 | H9: 200 | I9: 40 | J9: 360
A10: 2026-10-01 | B10: R002 | C10: Retail | D10: POS | E10: TREAT-QA | F10: QA Treat | G10: 1 | H10: 80 | I10: 0 | J10: 80

Sheet Source Notes
A1: Observation ID | B1: Area | C1: Source observation (not yet a QA failure) | D1: QA instruction | E1: Related cases
A2: OBS-01 | B2: Services Snooze / Retail Review / Prescriptive Approve-Dismiss | C2: Source includes buttons with no obvious action handler in current JSX. | D2: Test visible control; file a dead-action defect if no effect or explicit disabled state. | E2: SVC / RETAIL / EXTRA
A3: OBS-02 | B3: Forgot Password legacy states | C3: OTP/newPassword branches remain in source although successful send now closes dialog and uses emailed secure link. | D3: Test current email-link flow; N/A legacy branch only after reachability evidence. Misleading Send OTP copy is a wording defect. | E3: AUTH
A4: OBS-03 | B4: Settings system metadata | C4: Version, last-model-update, model list, transaction count and operational text include fixed literals. | D4: Compare to actual build/providers/data. Static factual claims must be labeled or logged as defects. | E4: SET
A5: OBS-04 | B5: MFA server-rendered enrollment | C5: Website enrollment requires live Next server; desktop bundle currently provides guidance rather than full first-time enrollment. | D5: Verify current documented desktop behavior; record release scope/requirement decision. Do not mark full native enrollment passed. | E5: AUTH / DESK
A6: OBS-05 | B6: Additional non-sidebar routes | C6: Executive Overview, Behavioral Bridges and Prescriptive Intelligence have direct pages; RecursiveLearning component has no current page wrapper. | D6: Test reachable direct routes; scope absent component explicitly, not as a passing feature. | E6: EXTRA
A7: OBS-06 | B7: Percentages and bounded displays | C7: Some incoming diagnostic percent outputs clamp extremes. | D7: Compare mathematical delta with UI; if clipped, the display must not claim an exact uncapped percentage. Record mismatch as defect. | E7: ROOT / QUALITY
A8: OBS-07 | B8: Forecast vs baseline source | C8: Operations defaults may use historical average unless Traffic forecast selected. | D8: Record selected source; verify date and hourly total. Never assume every run uses forecast automatically. | E8: WHATIF
A9: OBS-08 | B9: Inventory limitations | C9: Current snapshot lacks batch/expiry/retailSKU/reorder fields and guaranteed frozen multi-page timestamp. | D9: Unknowns stay unknown; do not demand unsupported business calculations or accept invented data. | E9: INV
A10: OBS-09 | B10: Historical empty periods | C10: No current records can mathematically show a 100% decline against prior data. | D10: Verify row counts/window; missing records must not become confident causal explanation of actual business loss. | E10: ROOT
A11: OBS-10 | B11: Installer scope | C11: Apple Silicon installer recently rebuilt; other platform files may be older. | D11: Verify tested artifact hash/build before assigning cross-platform results. | E11: DESK

Sheet Bug Log
A1: Bug ID | B1: Feature / Test ID | C1: Title | D1: Severity | E1: Build / Environment | F1: Steps to Reproduce | G1: Expected | H1: Actual | I1: Evidence | J1: Owner | K1: Status | L1: Retest / Resolution
A2: BUG-001
A3: BUG-002
A4: BUG-003
A5: BUG-004
A6: BUG-005
A7: BUG-006
A8: BUG-007
A9: BUG-008
A10: BUG-009
A11: BUG-010
A12: BUG-011
A13: BUG-012
... A61: BUG-060

Sheet Retest Log
A1: Execution ID | B1: Feature / Test / Parameter ID | C1: Build | D1: Scenario / Variant | E1: Status | F1: Actual Result | G1: Evidence | H1: Tester | I1: Date | J1: Bug ID
A2: RUN-001 | E2: Not Run
A3: RUN-002 | E3: Not Run
A4: RUN-003 | E4: Not Run
A5: RUN-004 | E5: Not Run
A6: RUN-005 | E6: Not Run
A7: RUN-006 | E7: Not Run
A8: RUN-007 | E8: Not Run
A9: RUN-008 | E9: Not Run
A10: RUN-009 | E10: Not Run
A11: RUN-010 | E11: Not Run
A12: RUN-011 | E12: Not Run
A13: RUN-012 | E13: Not Run
... A101: RUN-100 | E101: Not Run

Sheet Results Summary
A1: Metric | B1: Value
A2: Features — Not Run | B2: =COUNTIF('Feature Coverage'!F2:F82,"Not Run")
A3: Features — Pass | B3: =COUNTIF('Feature Coverage'!F2:F82,"Pass")
A4: Features — Fail | B4: =COUNTIF('Feature Coverage'!F2:F82,"Fail")
A5: Features — Blocked | B5: =COUNTIF('Feature Coverage'!F2:F82,"Blocked")
A6: Features — N/A | B6: =COUNTIF('Feature Coverage'!F2:F82,"N/A")
A7: Total features | B7: 81
A8: Total acceptance cases | B8: 239
A9: Event parameter variants | B9: 46
A10: Acceptance cases — Not Run | B10: =COUNTIF('Test Cases'!M2:M240,"Not Run")
A11: Acceptance cases — Pass | B11: =COUNTIF('Test Cases'!M2:M240,"Pass")
A12: Acceptance cases — Fail | B12: =COUNTIF('Test Cases'!M2:M240,"Fail")
A13: Acceptance cases — Blocked | B13: =COUNTIF('Test Cases'!M2:M240,"Blocked")
A14: Acceptance cases — N/A | B14: =COUNTIF('Test Cases'!M2:M240,"N/A")
A15: Execution rule | B15: Do not count archived per-click pack. Formula results calculate in Excel/LibreOffice; all results initially Not Run.
