Workbook

Sheet Start Here
A1: Item | B1: Details
A2: Purpose | B2: Manual QA specification for the current merged working tree, not an automated test report. All execution statuses start Not Run.
A3: Snapshot | B3: Prepared 2026-10-15; HEAD b9a1e2d plus uncommitted desktop, inventory, diagnostic and simulator changes. Record exact tested installer/build in Run Setup.
A4: Coverage | B4: 1070 functional/validation/data/workflow cases; 535 source-declared interaction checks; all 46 injectable event templates enumerated individually.
A5: How to execute | B5: Run P0 first, then P1, then P2. Open listed location; prepare data; follow steps; compare expected result; record actual, evidence, tester, time and bug ID.
A6: Every click | B6: One source declaration can render many runtime buttons. For EVERY visible row/card/option/hour/category/prompt/service/notification, create a separate Repeat Log execution tied to its base test/click ID. Never mark a whole dynamic family Pass after one item.
A7: Status definitions | B7: Not Run = untouched; Pass = observed expected result with evidence; Fail = observed mismatch; Blocked = cannot execute due to dependency/setup; N/A = confirmed out of scope/unreachable with evidence and lead sign-off.
A8: No automatic Pass | B8: Build success and prior automated tests are not manual QA evidence. A visible button that does nothing is a defect unless explicitly disabled/documented.
A9: Priorities | B9: P0: core access, key navigation, live simulation/events and end-to-end flows. P1: standard functional/data correctness. P2: additional route, visual and secondary compatibility checks.
A10: Platforms | B10: Primary: current Apple Silicon installer. Repeat desktop-specific cases on Windows x64 and Intel Mac only with corresponding current-build installers. Do not mark untested platforms Pass.
A11: Viewports | B11: Desktop 1440x900 and minimum app width; web 1920x1080; tablet 768x1024; phone 390x844 and 360x800. Record OS/browser/zoom/theme.
A12: Data protection | B12: Use QA DB/accounts, disposable products/recommendations/reports/uploads and approved QA campaign destination. Back up before retention/delete/import replacement. Do not execute destructive tests on live business data.
... A21: Tomorrow schedule | B21: Suggested order: setup/data oracle; login/navigation; uploads/data pages; AI tabs and simulator/events; reports/feedback/audit; settings; desktop/mobile/accessibility; end-to-end and retest. Full matrix may exceed one day: assign modules in parallel to human testers and document unexecuted scope.

Sheet Run Setup
A1: Field | B1: Value / Notes
A2: Run ID
A3: Execution date
A4: QA lead
A5: Tester assignments
A6: Git HEAD / working tree fingerprint
A7: Installer filename / SHA256
A8: OS / architecture
A9: Browser version (web)
A10: Viewport / zoom
A11: Backend environment (no secrets)
A12: Database snapshot / QA dataset
A13: Target date / timezone
... A19: Sign-off decision

Sheet Test Cases
A1: Test ID | B1: Module | C1: Location | D1: Control / Scenario | E1: Priority | F1: Type | G1: Preconditions | H1: Test Data | I1: Steps | J1: Expected Result | K1: Risk / Cleanup | L1: Source Reference | M1: Status | N1: Actual Result | O1: Bug ID | P1: Tester | Q1: Executed At | R1: Evidence
A2: AUTH-001 | B2: Login & Recovery | C2: /login | D2: Sign In — valid credentials and MFA | E2: P0 | F2: Authentication | G2: Signed out; use QA accounts only. | H2: QA-AUTH | I2: Enter authorized QA email/password; click Sign In; supply current authenticator code when requested. | J2: Authentication succeeds; dashboard opens only after required MFA; correct user is shown. | K2: Use dedicated QA account. Password/MFA changes: record cleanup and restore QA access. | L2: frontend/src/app/pages/Login.tsx | M2: Not Run
A3: AUTH-002 | B3: Login & Recovery | C3: /login | D3: Sign In — blank email | E3: P0 | F3: Authentication | G3: Signed out; use QA accounts only. | H3: QA-AUTH | I3: Leave email blank; enter password; click Sign In. | J3: Required-field validation appears; protected pages remain inaccessible. | K3: Use dedicated QA account. Password/MFA changes: record cleanup and restore QA access. | L3: frontend/src/app/pages/Login.tsx | M3: Not Run
A4: AUTH-003 | B4: Login & Recovery | C4: /login | D4: Sign In — blank password | E4: P0 | F4: Authentication | G4: Signed out; use QA accounts only. | H4: QA-AUTH | I4: Enter email; leave password blank; click Sign In. | J4: Password is required; no successful session is created. | K4: Use dedicated QA account. Password/MFA changes: record cleanup and restore QA access. | L4: frontend/src/app/pages/Login.tsx | M4: Not Run
A5: AUTH-004 | B5: Login & Recovery | C5: /login | D5: Sign In — malformed email | E5: P0 | F5: Authentication | G5: Signed out; use QA accounts only. | H5: QA-AUTH | I5: Enter not-an-email and a password; submit. | J5: Email validation rejects malformed input; no dashboard navigation. | K5: Use dedicated QA account. Password/MFA changes: record cleanup and restore QA access. | L5: frontend/src/app/pages/Login.tsx | M5: Not Run
A6: AUTH-005 | B6: Login & Recovery | C6: /login | D6: Sign In — incorrect password | E6: P0 | F6: Authentication | G6: Signed out; use QA accounts only. | H6: QA-AUTH | I6: Enter QA email and an incorrect password; submit. | J6: Generic authentication error; password/token is not exposed; remain signed out. | K6: Use dedicated QA account. Password/MFA changes: record cleanup and restore QA access. | L6: frontend/src/app/pages/Login.tsx | M6: Not Run
A7: AUTH-006 | B7: Login & Recovery | C7: /login | D7: Sign In — unrecognized email | E7: P0 | F7: Authentication | G7: Signed out; use QA accounts only. | H7: QA-AUTH | I7: Use unknown-qa@example.invalid and a password; submit. | J7: No account enumeration; generic failure; no protected data. | K7: Use dedicated QA account. Password/MFA changes: record cleanup and restore QA access. | L7: frontend/src/app/pages/Login.tsx | M7: Not Run
A8: AUTH-007 | B8: Login & Recovery | C8: /login | D8: Sign In — unauthorized account | E8: P0 | F8: Authentication | G8: Signed out; use QA accounts only. | H8: QA-AUTH | I8: Use a test Supabase user that is not the authorized owner; submit valid credentials. | J8: Unauthorized user cannot access the owner dashboard or protected APIs. | K8: Use dedicated QA account. Password/MFA changes: record cleanup and restore QA access. | L8: frontend/src/app/pages/Login.tsx | M8: Not Run
A9: AUTH-008 | B9: Login & Recovery | C9: /login | D9: Password eye — show | E9: P0 | F9: Authentication | G9: Signed out; use QA accounts only. | H9: QA-AUTH | I9: Enter a test password; click the eye icon once. | J9: Password becomes visible without changing its value. | K9: Use dedicated QA account. Password/MFA changes: record cleanup and restore QA access. | L9: frontend/src/app/pages/Login.tsx | M9: Not Run
A10: AUTH-009 | B10: Login & Recovery | C10: /login | D10: Password eye — hide | E10: P0 | F10: Authentication | G10: Signed out; use QA accounts only. | H10: QA-AUTH | I10: With password visible, click eye again. | J10: Password is masked; value is preserved. | K10: Use dedicated QA account. Password/MFA changes: record cleanup and restore QA access. | L10: frontend/src/app/pages/Login.tsx | M10: Not Run
A11: AUTH-010 | B11: Login & Recovery | C11: /login | D11: Sign In — keyboard submit | E11: P0 | F11: Authentication | G11: Signed out; use QA accounts only. | H11: QA-AUTH | I11: Fill valid inputs and press Enter. | J11: Same validation and MFA behavior as clicking Sign In; one submission. | K11: Use dedicated QA account. Password/MFA changes: record cleanup and restore QA access. | L11: frontend/src/app/pages/Login.tsx | M11: Not Run
A12: AUTH-011 | B12: Login & Recovery | C12: /login | D12: MFA — missing code | E12: P0 | F12: Authentication | G12: Signed out; use QA accounts only. | H12: QA-AUTH | I12: Trigger authenticator prompt; leave code blank; submit. | J12: MFA cannot be bypassed; protected pages remain blocked. | K12: Use dedicated QA account. Password/MFA changes: record cleanup and restore QA access. | L12: frontend/src/app/pages/Login.tsx | M12: Not Run
A13: AUTH-012 | B13: Login & Recovery | C13: /login | D13: MFA — valid current code | E13: P0 | F13: Authentication | G13: Signed out; use QA accounts only. | H13: QA-AUTH | I13: Enter the QA account's current 6-digit code and submit. | J13: AAL2 session established; dashboard opens. | K13: Use dedicated QA account. Password/MFA changes: record cleanup and restore QA access. | L13: frontend/src/app/pages/Login.tsx | M13: Not Run
... A1071: REPORT-044 | B1071: Smart Reports | C1071: /smart-reports | D1071: All sectors via three toggles | E1071: P1 | F1071: Functional | G1071: Signed in as authorized QA owner; open the listed location; required test data exists. | H1071: QA-BASE | I1071: Select Cafe, Retail and Services individually; generate report. | J1071: All three included exactly once; combined totals reconcile to sector totals. | K1071: Read-only | L1071: frontend/src/app/pages/SmartReports.tsx | M1071: Not Run

Sheet Click Checklist
A1: Click ID | B1: Source | C1: Page / Component | D1: Control | E1: Kind | F1: Setup / Locate | G1: Action | H1: Expected UI Response | I1: Repeat / Reachability | J1: Related Module | K1: Status | L1: Actual Result | M1: Bug ID | N1: Tester | O1: Evidence
A2: CLICK-0001 | B2: frontend/src/app/pages/AISimulation.tsx:2981 | C2: AISimulation | D2: Run Simulation Run | E2: Button | F2: Open matching page/tab/drawer/modal. Locate control by visible label and source reference; use QA data for write actions. | G2: Click once | H2: Control responds once; selected/expanded/loading state and target match the visible label; no unintended parent action or unrelated record change. Use the matching module case for persisted/data behavior. | I2: One declared UI target; still repeat across conditional contexts where it appears. | J2: Bundle Simulator | K2: Not Run
A3: CLICK-0002 | B3: frontend/src/app/pages/AISimulation.tsx:3090 | C3: AISimulation | D3: Icon / dynamic button control | E3: button | F3: Open matching page/tab/drawer/modal. Locate control by visible label and source reference; use QA data for write actions. | G3: Click once | H3: Only intended selection/filter/modal/visibility changes; repeat click follows toggle behavior if applicable; matching module case defines business result. | I3: Runtime/dynamic: repeat for EVERY displayed item/option; one separate execution row per click target. | J3: Bundle Simulator | K3: Not Run
A4: CLICK-0003 | B4: frontend/src/app/pages/AISimulation.tsx:3148 | C4: AISimulation | D4: Icon / dynamic Slider control | E4: Slider | F4: Open matching page/tab/drawer/modal. Locate control by visible label and source reference; use QA data for write actions. | G4: Click/drag minimum, midpoint and maximum separately | H4: Displayed value obeys bounds; keyboard adjustment works; dependent calculation matches selected value. | I4: Runtime/dynamic: repeat for EVERY displayed item/option; one separate execution row per click target. | J4: Bundle Simulator | K4: Not Run
A5: CLICK-0004 | B5: frontend/src/app/pages/AISimulation.tsx:3484 | C5: AISimulation | D5: {preset.tooltip} | E5: button | F5: Open matching page/tab/drawer/modal. Locate control by visible label and source reference; use QA data for write actions. | G5: Click once | H5: Only intended selection/filter/modal/visibility changes; repeat click follows toggle behavior if applicable; matching module case defines business result. | I5: Runtime/dynamic: repeat for EVERY displayed item/option; one separate execution row per click target. | J5: Bundle Simulator | K5: Not Run
A6: CLICK-0005 | B6: frontend/src/app/pages/AISimulation.tsx:3523 | C6: AISimulation | D6: Icon / dynamic Slider control | E6: Slider | F6: Open matching page/tab/drawer/modal. Locate control by visible label and source reference; use QA data for write actions. | G6: Click/drag minimum, midpoint and maximum separately | H6: Displayed value obeys bounds; keyboard adjustment works; dependent calculation matches selected value. | I6: Runtime/dynamic: repeat for EVERY displayed item/option; one separate execution row per click target. | J6: Bundle Simulator | K6: Not Run
A7: CLICK-0006 | B7: frontend/src/app/pages/AISimulation.tsx:3559 | C7: AISimulation | D7: Icon / dynamic Slider control | E7: Slider | F7: Open matching page/tab/drawer/modal. Locate control by visible label and source reference; use QA data for write actions. | G7: Click/drag minimum, midpoint and maximum separately | H7: Displayed value obeys bounds; keyboard adjustment works; dependent calculation matches selected value. | I7: Runtime/dynamic: repeat for EVERY displayed item/option; one separate execution row per click target. | J7: Bundle Simulator | K7: Not Run
A8: CLICK-0007 | B8: frontend/src/app/pages/AISimulation.tsx:3730 | C8: AISimulation | D8: Icon / dynamic Slider control | E8: Slider | F8: Open matching page/tab/drawer/modal. Locate control by visible label and source reference; use QA data for write actions. | G8: Click/drag minimum, midpoint and maximum separately | H8: Displayed value obeys bounds; keyboard adjustment works; dependent calculation matches selected value. | I8: Runtime/dynamic: repeat for EVERY displayed item/option; one separate execution row per click target. | J8: Bundle Simulator | K8: Not Run
A9: CLICK-0008 | B9: frontend/src/app/pages/AISimulation.tsx:3768 | C9: AISimulation | D9: FP-Growth Bundles | E9: button | F9: Open matching page/tab/drawer/modal. Locate control by visible label and source reference; use QA data for write actions. | G9: Click once | H9: Only intended selection/filter/modal/visibility changes; repeat click follows toggle behavior if applicable; matching module case defines business result. | I9: One declared UI target; still repeat across conditional contexts where it appears. | J9: Bundle Simulator | K9: Not Run
A10: CLICK-0009 | B10: frontend/src/app/pages/AISimulation.tsx:3779 | C10: AISimulation | D10: Icon / dynamic button control | E10: button | F10: Open matching page/tab/drawer/modal. Locate control by visible label and source reference; use QA data for write actions. | G10: Click once | H10: Control responds once; selected/expanded/loading state and target match the visible label; no unintended parent action or unrelated record change. Use the matching module case for persisted/data behavior. | I10: Runtime/dynamic: repeat for EVERY displayed item/option; one separate execution row per click target. | J10: Bundle Simulator | K10: Not Run
A11: CLICK-0010 | B11: frontend/src/app/pages/AISimulation.tsx:3796 | C11: AISimulation | D11: All Bundle Types | E11: button | F11: Open matching page/tab/drawer/modal. Locate control by visible label and source reference; use QA data for write actions. | G11: Click once | H11: Only intended selection/filter/modal/visibility changes; repeat click follows toggle behavior if applicable; matching module case defines business result. | I11: One declared UI target; still repeat across conditional contexts where it appears. | J11: Bundle Simulator | K11: Not Run
A12: CLICK-0011 | B12: frontend/src/app/pages/AISimulation.tsx:3807 | C12: AISimulation | D12: Icon / dynamic button control | E12: button | F12: Open matching page/tab/drawer/modal. Locate control by visible label and source reference; use QA data for write actions. | G12: Click once | H12: Only intended selection/filter/modal/visibility changes; repeat click follows toggle behavior if applicable; matching module case defines business result. | I12: Runtime/dynamic: repeat for EVERY displayed item/option; one separate execution row per click target. | J12: Bundle Simulator | K12: Not Run
A13: CLICK-0012 | B13: frontend/src/app/pages/AISimulation.tsx:3820 | C13: AISimulation | D13: Filter to show only bundles with at least 5% support across customer receipts. | E13: button | F13: Open matching page/tab/drawer/modal. Locate control by visible label and source reference; use QA data for write actions. | G13: Click once | H13: Only intended selection/filter/modal/visibility changes; repeat click follows toggle behavior if applicable; matching module case defines business result. | I13: One declared UI target; still repeat across conditional contexts where it appears. | J13: Bundle Simulator | K13: Not Run
... A536: CLICK-0535 | B536: frontend/pages/reset-password.tsx:26 | C536: reset-password | D536: Update password | E536: button | F536: Open matching page/tab/drawer/modal. Locate control by visible label and source reference; use QA data for write actions. | G536: Click once | H536: Control responds once; selected/expanded/loading state and target match the visible label; no unintended parent action or unrelated record change. Use the matching module case for persisted/data behavior. | I536: One declared UI target; still repeat across conditional contexts where it appears. | J536: Shared component / see module cases | K536: Not Run

Sheet Repeat Log
A1: Execution ID | B1: Base Test / Click ID | C1: Runtime target / exact label / UUID | D1: Context / date / page / scenario | E1: Input / option / boundary | F1: Steps / action | G1: Expected result | H1: Status | I1: Actual Result | J1: Bug ID | K1: Tester | L1: Executed At | M1: Evidence
A2: REP-0001 | H2: Not Run
A3: REP-0002 | H3: Not Run
A4: REP-0003 | H4: Not Run
A5: REP-0004 | H5: Not Run
A6: REP-0005 | H6: Not Run
A7: REP-0006 | H7: Not Run
A8: REP-0007 | H8: Not Run
A9: REP-0008 | H9: Not Run
A10: REP-0009 | H10: Not Run
A11: REP-0010 | H11: Not Run
A12: REP-0011 | H12: Not Run
A13: REP-0012 | H13: Not Run
... A201: REP-0200 | H201: Not Run

Sheet Bug Log
A1: Bug ID | B1: Related Test / Click ID | C1: Title | D1: Severity | E1: Priority | F1: Environment / Build | G1: Preconditions / Data | H1: Reproduction Steps | I1: Expected Result | J1: Actual Result | K1: Evidence | L1: Owner | M1: Bug Status | N1: Fix Build | O1: Retest ID | P1: Retest Result
A2: BUG-001
A3: BUG-002
A4: BUG-003
A5: BUG-004
A6: BUG-005
A7: BUG-006
A8: BUG-007
A9: BUG-008
A10: BUG-009
A11: BUG-010
A12: BUG-011
A13: BUG-012
... A101: BUG-100

Sheet Test Data
A1: Data ID | B1: Fixture / Setup | C1: Oracle / Cleanup
A2: QA-BASE | B2: Authorized QA owner, known datasets, backend and required providers available | C2: Record environment/build and restore baseline between state-changing cases. Never paste passwords/tokens into workbook.
A3: QA-AUTH | B3: Enrolled QA owner, unknown email, unauthorized QA user, disposable unenrolled QA account and QA inbox | C3: Keep credentials in approved secret store. Password/MFA mutations only dedicated test accounts.
A4: QA-UPLOAD | B4: Approved POS CSV/Excel, Shopee and TikTok export copies; PetHub blocked-input fixture; duplicate, malformed, empty and size-boundary variants | C4: Use real accepted vendor schema; ledger file is NOT an uploader template. Record raw row count, rejected count and accepted totals before running.
A5: QA-LEDGER | B5: QA_REFERENCE_LEDGER.csv; normalized reference rows, 2026-09-30 vs 2026-10-01 | C5: Map through supported test import/seed mechanism in isolated DB. Expected: prior 900; current gross1320, discounts110, net1210; 5 distinct transactions; 9 units; AOV242; Cafe320/2orders/5units; Services450/1order/1unit; Retail440/2orders/3units; totaldelta310 (34.444...%).
A6: QA-FORECAST | B6: Date with known traffic/hourly forecast plus production/holdout/fixed-window outputs | C6: Save actual API payload, date/hour range and sector counts as oracle. Forecast totals are not unique-person counts unless explicitly supported.
A7: QA-SIM | B7: Custom scenario: date2026-10-15, open08:00, duration600min, seed12345; Services3staff/3stations, Cafe2staff/2stations, cashier1; enough supply/demand; random events OFF for controlled comparisons | C7: Record effective exported config. Use 120 customers for event workload or a smaller run for lifecycle. Effects may be zero when no eligible future customers; create targeted demand fixture instead of inventing expected impact.
A8: QA-INVENTORY | B8: QA Pet Shop products: active stock12, active stock0, active stocknull, inactive stock7; nullSKU/threshold; >200 products for pagination; one disposable removal | C8: Record real UUIDs from QA source; no fake fixed UUIDs required. Restore stock/active/category/deletion test fixtures after run. Source response/API is quantity oracle.
A9: QA-BUNDLES | B9: Receipts with known co-purchase pair; enough support; distinct catalog products; QA-prefixed manual bundles | C9: Hand-calculate support=count(A&B)/receipts; confidence=count(A&B)/count(A); lift=confidence/support(B); empty-support fixture too.
A10: QA-CAMPAIGN | B10: Disposable recommendation and authorized QA publish destination | C10: Publishing is external side effect. If no approved QA target, mark publication cases Blocked; do not publish to production.
A11: QA-REPORT | B11: Known-window data, unique QA title, existing and generated disposable reports; no-data and partial-data windows | C11: Include 30-day boundary and >30-day window. Retain exports for verification; clean created reports afterward.
A12: QA-FEEDBACK | B12: Separate fresh active recommendations for helpful, unhelpful and end-promotion cases | C12: Feedback changes model inputs; use isolated data and avoid recycling same record for incompatible paths.
... A15: QA-DESKTOP | B15: Matching current installers and dedicated app profile per OS | C15: Record SHA256, architecture, installer date and OS version. Do not assume old Windows/Intel installers contain latest merge.

Sheet Reference Ledger
A1: Business date | B1: Transaction ID | C1: Sector | D1: Channel | E1: Reference SKU | F1: Product | G1: Qty | H1: Unit Price | I1: Discount | J1: Expected Net
A2: 2026-09-30 | B2: PC001 | C2: Cafe | D2: POS | E2: LATTE-QA | F2: QA Latte | G2: 3 | H2: 100 | I2: 0 | J2: 300
A3: 2026-09-30 | B3: PS001 | C3: Services | D3: POS | E3: GROOM-QA | F3: QA Grooming | G3: 1 | H3: 400 | I3: 0 | J3: 400
A4: 2026-09-30 | B4: PR001 | C4: Retail | D4: POS | E4: FOOD-QA | F4: QA Pet Food | G4: 1 | H4: 200 | I4: 0 | J4: 200
A5: 2026-10-01 | B5: C001 | C5: Cafe | D5: POS | E5: LATTE-QA | F5: QA Latte | G5: 2 | H5: 100 | I5: 20 | J5: 180
A6: 2026-10-01 | B6: C001 | C6: Cafe | D6: POS | E6: MUFFIN-QA | F6: QA Muffin | G6: 1 | H6: 60 | I6: 0 | J6: 60
A7: 2026-10-01 | B7: C002 | C7: Cafe | D7: POS | E7: COOKIE-QA | F7: QA Pet Cookie | G7: 2 | H7: 40 | I7: 0 | J7: 80
A8: 2026-10-01 | B8: S001 | C8: Services | D8: POS | E8: GROOM-QA | F8: QA Grooming | G8: 1 | H8: 500 | I8: 50 | J8: 450
A9: 2026-10-01 | B9: R001 | C9: Retail | D9: POS | E9: FOOD-QA | F9: QA Pet Food | G9: 2 | H9: 200 | I9: 40 | J9: 360
A10: 2026-10-01 | B10: R002 | C10: Retail | D10: POS | E10: TREAT-QA | F10: QA Treat | G10: 1 | H10: 80 | I10: 0 | J10: 80

Sheet Source Review Notes
A1: Observation ID | B1: Area | C1: Source observation (not yet a QA failure) | D1: QA instruction | E1: Related cases
A2: OBS-01 | B2: Services Snooze / Retail Review / Prescriptive Approve-Dismiss | C2: Source includes buttons with no obvious action handler in current JSX. | D2: Test visible control; file a dead-action defect if no effect or explicit disabled state. | E2: SVC / RETAIL / EXTRA
A3: OBS-02 | B3: Forgot Password legacy states | C3: OTP/newPassword branches remain in source although successful send now closes dialog and uses emailed secure link. | D3: Test current email-link flow; N/A legacy branch only after reachability evidence. Misleading Send OTP copy is a wording defect. | E3: AUTH / Click Checklist
A4: OBS-03 | B4: Settings system metadata | C4: Version, last-model-update, model list, transaction count and operational text include fixed literals. | D4: Compare to actual build/providers/data. Static factual claims must be labeled or logged as defects. | E4: SET
A5: OBS-04 | B5: MFA server-rendered enrollment | C5: Website enrollment requires live Next server; desktop bundle currently provides guidance rather than full first-time enrollment. | D5: Verify current documented desktop behavior; record release scope/requirement decision. Do not mark full native enrollment passed. | E5: AUTH / DESK
A6: OBS-05 | B6: Additional non-sidebar routes | C6: Executive Overview, Behavioral Bridges and Prescriptive Intelligence have direct pages; RecursiveLearning component has no current page wrapper. | D6: Test reachable direct routes; scope absent component explicitly, not as a passing feature. | E6: EXTRA / Click Checklist
A7: OBS-06 | B7: Percentages and bounded displays | C7: Some incoming diagnostic percent outputs clamp extremes. | D7: Compare mathematical delta with UI; if clipped, the display must not claim an exact uncapped percentage. Record mismatch as defect. | E7: ROOT / QUALITY
A8: OBS-07 | B8: Forecast vs baseline source | C8: Operations defaults may use historical average unless Traffic forecast selected. | D8: Record selected source; verify date and hourly total. Never assume every run uses forecast automatically. | E8: WHATIF
A9: OBS-08 | B9: Inventory limitations | C9: Current snapshot lacks batch/expiry/retailSKU/reorder fields and guaranteed frozen multi-page timestamp. | D9: Unknowns stay unknown; do not demand unsupported business calculations or accept invented data. | E9: INV
A10: OBS-09 | B10: Historical empty periods | C10: No current records can mathematically show a 100% decline against prior data. | D10: Verify row counts/window; missing records must not become confident causal explanation of actual business loss. | E10: ROOT
A11: OBS-10 | B11: Installer scope | C11: Apple Silicon installer recently rebuilt; other platform files may be older. | D11: Verify tested artifact hash/build before assigning cross-platform results. | E11: DESK

Sheet Coverage Map
A1: Module | B1: Location | C1: Primary Source | D1: Case Count | E1: P0 Count | F1: Test IDs | G1: Coverage notes
A2: Login & Recovery | B2: /login | C2: frontend/src/app/pages/Login.tsx | D2: 34 | E2: 34 | F2: AUTH-001, AUTH-002, AUTH-003, AUTH-004, AUTH-005, AUTH-006, AUTH-007, AUTH-008, AUTH-009, AUTH-010, AUTH-011, AUTH-012, AUTH-013, AUTH-014, AUTH-015, AUTH-016, AUTH-017, AUTH-018, AUTH-019, AUTH-020, AUTH-021, AUTH-022, AUTH-023, AUTH-024, AUTH-025, AUTH-026, AUTH-027, AUTH-028, AUTH-029, AUTH-030, AUTH-031, AUTH-032, AUTH-033, AUTH-034 | G2: Manual functional coverage; supplement every dynamic target with Repeat Log.
A3: Navigation & Header | B3: All main pages | C3: frontend/src/app/components/Header.tsx | D3: 53 | E3: 10 | F3: NAV-001, NAV-002, NAV-003, NAV-004, NAV-005, NAV-006, NAV-007, NAV-008, NAV-009, NAV-010, NAV-011, NAV-012, NAV-013, NAV-014, NAV-015, NAV-016, NAV-017, NAV-018, NAV-019, NAV-020, NAV-021, NAV-022, NAV-023, NAV-024, NAV-025, NAV-026, NAV-027, NAV-028, NAV-029, NAV-030, NAV-031, NAV-032, NAV-033, NAV-034, NAV-035, NAV-036, NAV-037, NAV-038, NAV-039, NAV-040, NAV-041, NAV-042, NAV-043, NAV-044, NAV-045, NAV-046, NAV-047, NAV-048, NAV-049, NAV-050, NAV-051, NAV-052, NAV-053 | G3: Manual functional coverage; supplement every dynamic target with Repeat Log.
A4: Data Ingestion | B4: Header > Data Ingestion | C4: frontend/src/app/components/DataIngestion.tsx | D4: 29 | E4: 0 | F4: UPLOAD-001, UPLOAD-002, UPLOAD-003, UPLOAD-004, UPLOAD-005, UPLOAD-006, UPLOAD-007, UPLOAD-008, UPLOAD-009, UPLOAD-010, UPLOAD-011, UPLOAD-012, UPLOAD-013, UPLOAD-014, UPLOAD-015, UPLOAD-016, UPLOAD-017, UPLOAD-018, UPLOAD-019, UPLOAD-020, UPLOAD-021, UPLOAD-022, UPLOAD-023, UPLOAD-024, UPLOAD-025, UPLOAD-026, UPLOAD-027, UPLOAD-028, UPLOAD-029 | G4: Manual functional coverage; supplement every dynamic target with Repeat Log.
A5: Home | B5: / | C5: frontend/src/app/pages/Home.tsx | D5: 52 | E5: 0 | F5: HOME-001, HOME-002, HOME-003, HOME-004, HOME-005, HOME-006, HOME-007, HOME-008, HOME-009, HOME-010, HOME-011, HOME-012, HOME-013, HOME-014, HOME-015, HOME-016, HOME-017, HOME-018, HOME-019, HOME-020, HOME-021, HOME-022, HOME-023, HOME-024, HOME-025, HOME-026, HOME-027, HOME-028, HOME-029, HOME-030, HOME-031, HOME-032, HOME-033, HOME-034, HOME-035, HOME-036, HOME-037, HOME-038, HOME-039, HOME-040, HOME-041, HOME-042, HOME-043, HOME-044, HOME-045, HOME-046, HOME-047, HOME-048, HOME-049, HOME-050, HOME-051, HOME-052 | G5: Manual functional coverage; supplement every dynamic target with Repeat Log.
A6: Cafe | B6: /cafe | C6: frontend/src/app/pages/Cafe.tsx | D6: 81 | E6: 0 | F6: CAFE-001, CAFE-002, CAFE-003, CAFE-004, CAFE-005, CAFE-006, CAFE-007, CAFE-008, CAFE-009, CAFE-010, CAFE-011, CAFE-012, CAFE-013, CAFE-014, CAFE-015, CAFE-016, CAFE-017, CAFE-018, CAFE-019, CAFE-020, CAFE-021, CAFE-022, CAFE-023, CAFE-024, CAFE-025, CAFE-026, CAFE-027, CAFE-028, CAFE-029, CAFE-030, CAFE-031, CAFE-032, CAFE-033, CAFE-034, CAFE-035, CAFE-036, CAFE-037, CAFE-038, CAFE-039, CAFE-040, CAFE-041, CAFE-042, CAFE-043, CAFE-044, CAFE-045, CAFE-046, CAFE-047, CAFE-048, CAFE-049, CAFE-050, CAFE-051, CAFE-052, CAFE-053, CAFE-054, CAFE-055, CAFE-056, CAFE-057, CAFE-058, CAFE-059, CAFE-060, CAFE-061, CAFE-062, CAFE-063, CAFE-064, CAFE-065, CAFE-066, CAFE-067, CAFE-068, CAFE-069, CAFE-070, CAFE-071, CAFE-072, CAFE-073, CAFE-074, CAFE-075, CAFE-076, CAFE-077, CAFE-078, CAFE-079, CAFE-080, CAFE-081 | G6: Manual functional coverage; supplement every dynamic target with Repeat Log.
A7: Services | B7: /services | C7: frontend/src/app/pages/Services.tsx | D7: 68 | E7: 0 | F7: SVC-001, SVC-002, SVC-003, SVC-004, SVC-005, SVC-006, SVC-007, SVC-008, SVC-009, SVC-010, SVC-011, SVC-012, SVC-013, SVC-014, SVC-015, SVC-016, SVC-017, SVC-018, SVC-019, SVC-020, SVC-021, SVC-022, SVC-023, SVC-024, SVC-025, SVC-026, SVC-027, SVC-028, SVC-029, SVC-030, SVC-031, SVC-032, SVC-033, SVC-034, SVC-035, SVC-036, SVC-037, SVC-038, SVC-039, SVC-040, SVC-041, SVC-042, SVC-043, SVC-044, SVC-045, SVC-046, SVC-047, SVC-048, SVC-049, SVC-050, SVC-051, SVC-052, SVC-053, SVC-054, SVC-055, SVC-056, SVC-057, SVC-058, SVC-059, SVC-060, SVC-061, SVC-062, SVC-063, SVC-064, SVC-065, SVC-066, SVC-067, SVC-068 | G7: Manual functional coverage; supplement every dynamic target with Repeat Log.
A8: Retail | B8: /retail | C8: frontend/src/app/pages/Retail.tsx | D8: 27 | E8: 0 | F8: RETAIL-001, RETAIL-002, RETAIL-003, RETAIL-004, RETAIL-005, RETAIL-006, RETAIL-007, RETAIL-008, RETAIL-009, RETAIL-010, RETAIL-011, RETAIL-012, RETAIL-013, RETAIL-014, RETAIL-015, RETAIL-016, RETAIL-017, RETAIL-018, RETAIL-019, RETAIL-020, RETAIL-021, RETAIL-022, RETAIL-023, RETAIL-024, RETAIL-025, RETAIL-026, RETAIL-027 | G8: Manual functional coverage; supplement every dynamic target with Repeat Log.
A9: Inventory Monitor | B9: /retail > Inventory Health Monitor | C9: frontend/src/app/components/RetailInventoryMonitor.tsx | D9: 35 | E9: 0 | F9: INV-001, INV-002, INV-003, INV-004, INV-005, INV-006, INV-007, INV-008, INV-009, INV-010, INV-011, INV-012, INV-013, INV-014, INV-015, INV-016, INV-017, INV-018, INV-019, INV-020, INV-021, INV-022, INV-023, INV-024, INV-025, INV-026, INV-027, INV-028, INV-029, INV-030, INV-031, INV-032, INV-033, INV-034, INV-035 | G9: Manual functional coverage; supplement every dynamic target with Repeat Log.
A10: Bundle Simulator | B10: /ai-simulation > Bundle Simulator | C10: frontend/src/app/pages/AISimulation.tsx | D10: 61 | E10: 0 | F10: BUNDLE-001, BUNDLE-002, BUNDLE-003, BUNDLE-004, BUNDLE-005, BUNDLE-006, BUNDLE-007, BUNDLE-008, BUNDLE-009, BUNDLE-010, BUNDLE-011, BUNDLE-012, BUNDLE-013, BUNDLE-014, BUNDLE-015, BUNDLE-016, BUNDLE-017, BUNDLE-018, BUNDLE-019, BUNDLE-020, BUNDLE-021, BUNDLE-022, BUNDLE-023, BUNDLE-024, BUNDLE-025, BUNDLE-026, BUNDLE-027, BUNDLE-028, BUNDLE-029, BUNDLE-030, BUNDLE-031, BUNDLE-032, BUNDLE-033, BUNDLE-034, BUNDLE-035, BUNDLE-036, BUNDLE-037, BUNDLE-038, BUNDLE-039, BUNDLE-040, BUNDLE-041, BUNDLE-042, BUNDLE-043, BUNDLE-044, BUNDLE-045, BUNDLE-046, BUNDLE-047, BUNDLE-048, BUNDLE-049, BUNDLE-050, BUNDLE-051, BUNDLE-052, BUNDLE-053, BUNDLE-054, BUNDLE-055, BUNDLE-056, BUNDLE-057, BUNDLE-058, BUNDLE-059, BUNDLE-060, BUNDLE-061 | G10: Manual functional coverage; supplement every dynamic target with Repeat Log.
A11: Pricing Laboratory | B11: /ai-simulation > Pricing Laboratory | C11: frontend/src/app/pages/AISimulation.tsx | D11: 16 | E11: 0 | F11: PRICE-001, PRICE-002, PRICE-003, PRICE-004, PRICE-005, PRICE-006, PRICE-007, PRICE-008, PRICE-009, PRICE-010, PRICE-011, PRICE-012, PRICE-013, PRICE-014, PRICE-015, PRICE-016 | G11: Manual functional coverage; supplement every dynamic target with Repeat Log.
A12: Traffic Optimizer | B12: /ai-simulation > Traffic Optimizer | C12: frontend/src/app/pages/AISimulation.tsx | D12: 19 | E12: 0 | F12: TRAFFIC-001, TRAFFIC-002, TRAFFIC-003, TRAFFIC-004, TRAFFIC-005, TRAFFIC-006, TRAFFIC-007, TRAFFIC-008, TRAFFIC-009, TRAFFIC-010, TRAFFIC-011, TRAFFIC-012, TRAFFIC-013, TRAFFIC-014, TRAFFIC-015, TRAFFIC-016, TRAFFIC-017, TRAFFIC-018, TRAFFIC-019 | G12: Manual functional coverage; supplement every dynamic target with Repeat Log.
A13: Operations What-If | B13: /ai-simulation > Operations What-If | C13: frontend/src/app/components/simulation/OperationsWhatIf.tsx | D13: 124 | E13: 53 | F13: WHATIF-001, WHATIF-002, WHATIF-003, WHATIF-004, WHATIF-005, WHATIF-006, WHATIF-007, WHATIF-008, WHATIF-009, WHATIF-010, WHATIF-011, WHATIF-012, WHATIF-013, WHATIF-014, WHATIF-015, WHATIF-016, WHATIF-017, WHATIF-018, WHATIF-019, WHATIF-020, WHATIF-021, WHATIF-022, WHATIF-023, WHATIF-024, WHATIF-025, WHATIF-026, WHATIF-027, WHATIF-028, WHATIF-029, WHATIF-030, WHATIF-031, WHATIF-032, WHATIF-033, WHATIF-034, WHATIF-035, WHATIF-036, WHATIF-037, WHATIF-038, WHATIF-039, WHATIF-040, WHATIF-041, WHATIF-042, WHATIF-043, WHATIF-044, WHATIF-045, WHATIF-046, WHATIF-047, WHATIF-048, WHATIF-049, WHATIF-050, WHATIF-051, WHATIF-052, WHATIF-053, WHATIF-054, WHATIF-055, WHATIF-056, WHATIF-057, WHATIF-058, WHATIF-059, WHATIF-060, WHATIF-061, WHATIF-062, WHATIF-063, WHATIF-064, WHATIF-065, WHATIF-066, WHATIF-067, WHATIF-068, WHATIF-069, WHATIF-070, WHATIF-071, WHATIF-072, WHATIF-073, WHATIF-074, WHATIF-075, WHATIF-076, WHATIF-077, WHATIF-078, WHATIF-079, WHATIF-080, WHATIF-081, WHATIF-082, WHATIF-083, WHATIF-084, WHATIF-085, WHATIF-086, WHATIF-087, WHATIF-088, WHATIF-089, WHATIF-090, WHATIF-091, WHATIF-092, WHATIF-093, WHATIF-094, WHATIF-095, WHATIF-096, WHATIF-097, WHATIF-098, WHATIF-099, WHATIF-100, WHATIF-101, WHATIF-102, WHATIF-103, WHATIF-104, WHATIF-105, WHATIF-106, WHATIF-107, WHATIF-108, WHATIF-109, WHATIF-110, WHATIF-111, WHATIF-112, WHATIF-113, WHATIF-114, WHATIF-115, WHATIF-116, WHATIF-117, WHATIF-118, WHATIF-119, WHATIF-120, WHATIF-121, WHATIF-122, WHATIF-123, WHATIF-124 | G13: Manual functional coverage; supplement every dynamic target with Repeat Log.
... A27: End-to-end | B27: Cross-module | C27: docs/qa/README.md | D27: 7 | E27: 7 | F27: E2E-001, E2E-002, E2E-003, E2E-004, E2E-005, E2E-006, E2E-007 | G27: Manual functional coverage; supplement every dynamic target with Repeat Log.

Sheet Results Summary
A1: Module / Matrix | B1: Total | C1: Not Run | D1: Pass | E1: Fail | F1: Blocked | G1: N/A | H1: Executed % | I1: Pass % of executed
A2: Login & Recovery | B2: =COUNTIF('Test Cases'!$B$2:$B$1071,A2) | C2: =COUNTIFS('Test Cases'!$B$2:$B$1071,A2,'Test Cases'!$M$2:$M$1071,"Not Run") | D2: =COUNTIFS('Test Cases'!$B$2:$B$1071,A2,'Test Cases'!$M$2:$M$1071,"Pass") | E2: =COUNTIFS('Test Cases'!$B$2:$B$1071,A2,'Test Cases'!$M$2:$M$1071,"Fail") | F2: =COUNTIFS('Test Cases'!$B$2:$B$1071,A2,'Test Cases'!$M$2:$M$1071,"Blocked") | G2: =COUNTIFS('Test Cases'!$B$2:$B$1071,A2,'Test Cases'!$M$2:$M$1071,"N/A") | H2: =IFERROR((D2+E2)/(B2-G2),0) | I2: =IFERROR(D2/(D2+E2),0)
A3: Navigation & Header | B3: =COUNTIF('Test Cases'!$B$2:$B$1071,A3) | C3: =COUNTIFS('Test Cases'!$B$2:$B$1071,A3,'Test Cases'!$M$2:$M$1071,"Not Run") | D3: =COUNTIFS('Test Cases'!$B$2:$B$1071,A3,'Test Cases'!$M$2:$M$1071,"Pass") | E3: =COUNTIFS('Test Cases'!$B$2:$B$1071,A3,'Test Cases'!$M$2:$M$1071,"Fail") | F3: =COUNTIFS('Test Cases'!$B$2:$B$1071,A3,'Test Cases'!$M$2:$M$1071,"Blocked") | G3: =COUNTIFS('Test Cases'!$B$2:$B$1071,A3,'Test Cases'!$M$2:$M$1071,"N/A") | H3: =IFERROR((D3+E3)/(B3-G3),0) | I3: =IFERROR(D3/(D3+E3),0)
A4: Data Ingestion | B4: =COUNTIF('Test Cases'!$B$2:$B$1071,A4) | C4: =COUNTIFS('Test Cases'!$B$2:$B$1071,A4,'Test Cases'!$M$2:$M$1071,"Not Run") | D4: =COUNTIFS('Test Cases'!$B$2:$B$1071,A4,'Test Cases'!$M$2:$M$1071,"Pass") | E4: =COUNTIFS('Test Cases'!$B$2:$B$1071,A4,'Test Cases'!$M$2:$M$1071,"Fail") | F4: =COUNTIFS('Test Cases'!$B$2:$B$1071,A4,'Test Cases'!$M$2:$M$1071,"Blocked") | G4: =COUNTIFS('Test Cases'!$B$2:$B$1071,A4,'Test Cases'!$M$2:$M$1071,"N/A") | H4: =IFERROR((D4+E4)/(B4-G4),0) | I4: =IFERROR(D4/(D4+E4),0)
A5: Home | B5: =COUNTIF('Test Cases'!$B$2:$B$1071,A5) | C5: =COUNTIFS('Test Cases'!$B$2:$B$1071,A5,'Test Cases'!$M$2:$M$1071,"Not Run") | D5: =COUNTIFS('Test Cases'!$B$2:$B$1071,A5,'Test Cases'!$M$2:$M$1071,"Pass") | E5: =COUNTIFS('Test Cases'!$B$2:$B$1071,A5,'Test Cases'!$M$2:$M$1071,"Fail") | F5: =COUNTIFS('Test Cases'!$B$2:$B$1071,A5,'Test Cases'!$M$2:$M$1071,"Blocked") | G5: =COUNTIFS('Test Cases'!$B$2:$B$1071,A5,'Test Cases'!$M$2:$M$1071,"N/A") | H5: =IFERROR((D5+E5)/(B5-G5),0) | I5: =IFERROR(D5/(D5+E5),0)
A6: Cafe | B6: =COUNTIF('Test Cases'!$B$2:$B$1071,A6) | C6: =COUNTIFS('Test Cases'!$B$2:$B$1071,A6,'Test Cases'!$M$2:$M$1071,"Not Run") | D6: =COUNTIFS('Test Cases'!$B$2:$B$1071,A6,'Test Cases'!$M$2:$M$1071,"Pass") | E6: =COUNTIFS('Test Cases'!$B$2:$B$1071,A6,'Test Cases'!$M$2:$M$1071,"Fail") | F6: =COUNTIFS('Test Cases'!$B$2:$B$1071,A6,'Test Cases'!$M$2:$M$1071,"Blocked") | G6: =COUNTIFS('Test Cases'!$B$2:$B$1071,A6,'Test Cases'!$M$2:$M$1071,"N/A") | H6: =IFERROR((D6+E6)/(B6-G6),0) | I6: =IFERROR(D6/(D6+E6),0)
A7: Services | B7: =COUNTIF('Test Cases'!$B$2:$B$1071,A7) | C7: =COUNTIFS('Test Cases'!$B$2:$B$1071,A7,'Test Cases'!$M$2:$M$1071,"Not Run") | D7: =COUNTIFS('Test Cases'!$B$2:$B$1071,A7,'Test Cases'!$M$2:$M$1071,"Pass") | E7: =COUNTIFS('Test Cases'!$B$2:$B$1071,A7,'Test Cases'!$M$2:$M$1071,"Fail") | F7: =COUNTIFS('Test Cases'!$B$2:$B$1071,A7,'Test Cases'!$M$2:$M$1071,"Blocked") | G7: =COUNTIFS('Test Cases'!$B$2:$B$1071,A7,'Test Cases'!$M$2:$M$1071,"N/A") | H7: =IFERROR((D7+E7)/(B7-G7),0) | I7: =IFERROR(D7/(D7+E7),0)
A8: Retail | B8: =COUNTIF('Test Cases'!$B$2:$B$1071,A8) | C8: =COUNTIFS('Test Cases'!$B$2:$B$1071,A8,'Test Cases'!$M$2:$M$1071,"Not Run") | D8: =COUNTIFS('Test Cases'!$B$2:$B$1071,A8,'Test Cases'!$M$2:$M$1071,"Pass") | E8: =COUNTIFS('Test Cases'!$B$2:$B$1071,A8,'Test Cases'!$M$2:$M$1071,"Fail") | F8: =COUNTIFS('Test Cases'!$B$2:$B$1071,A8,'Test Cases'!$M$2:$M$1071,"Blocked") | G8: =COUNTIFS('Test Cases'!$B$2:$B$1071,A8,'Test Cases'!$M$2:$M$1071,"N/A") | H8: =IFERROR((D8+E8)/(B8-G8),0) | I8: =IFERROR(D8/(D8+E8),0)
A9: Inventory Monitor | B9: =COUNTIF('Test Cases'!$B$2:$B$1071,A9) | C9: =COUNTIFS('Test Cases'!$B$2:$B$1071,A9,'Test Cases'!$M$2:$M$1071,"Not Run") | D9: =COUNTIFS('Test Cases'!$B$2:$B$1071,A9,'Test Cases'!$M$2:$M$1071,"Pass") | E9: =COUNTIFS('Test Cases'!$B$2:$B$1071,A9,'Test Cases'!$M$2:$M$1071,"Fail") | F9: =COUNTIFS('Test Cases'!$B$2:$B$1071,A9,'Test Cases'!$M$2:$M$1071,"Blocked") | G9: =COUNTIFS('Test Cases'!$B$2:$B$1071,A9,'Test Cases'!$M$2:$M$1071,"N/A") | H9: =IFERROR((D9+E9)/(B9-G9),0) | I9: =IFERROR(D9/(D9+E9),0)
A10: Bundle Simulator | B10: =COUNTIF('Test Cases'!$B$2:$B$1071,A10) | C10: =COUNTIFS('Test Cases'!$B$2:$B$1071,A10,'Test Cases'!$M$2:$M$1071,"Not Run") | D10: =COUNTIFS('Test Cases'!$B$2:$B$1071,A10,'Test Cases'!$M$2:$M$1071,"Pass") | E10: =COUNTIFS('Test Cases'!$B$2:$B$1071,A10,'Test Cases'!$M$2:$M$1071,"Fail") | F10: =COUNTIFS('Test Cases'!$B$2:$B$1071,A10,'Test Cases'!$M$2:$M$1071,"Blocked") | G10: =COUNTIFS('Test Cases'!$B$2:$B$1071,A10,'Test Cases'!$M$2:$M$1071,"N/A") | H10: =IFERROR((D10+E10)/(B10-G10),0) | I10: =IFERROR(D10/(D10+E10),0)
A11: Pricing Laboratory | B11: =COUNTIF('Test Cases'!$B$2:$B$1071,A11) | C11: =COUNTIFS('Test Cases'!$B$2:$B$1071,A11,'Test Cases'!$M$2:$M$1071,"Not Run") | D11: =COUNTIFS('Test Cases'!$B$2:$B$1071,A11,'Test Cases'!$M$2:$M$1071,"Pass") | E11: =COUNTIFS('Test Cases'!$B$2:$B$1071,A11,'Test Cases'!$M$2:$M$1071,"Fail") | F11: =COUNTIFS('Test Cases'!$B$2:$B$1071,A11,'Test Cases'!$M$2:$M$1071,"Blocked") | G11: =COUNTIFS('Test Cases'!$B$2:$B$1071,A11,'Test Cases'!$M$2:$M$1071,"N/A") | H11: =IFERROR((D11+E11)/(B11-G11),0) | I11: =IFERROR(D11/(D11+E11),0)
A12: Traffic Optimizer | B12: =COUNTIF('Test Cases'!$B$2:$B$1071,A12) | C12: =COUNTIFS('Test Cases'!$B$2:$B$1071,A12,'Test Cases'!$M$2:$M$1071,"Not Run") | D12: =COUNTIFS('Test Cases'!$B$2:$B$1071,A12,'Test Cases'!$M$2:$M$1071,"Pass") | E12: =COUNTIFS('Test Cases'!$B$2:$B$1071,A12,'Test Cases'!$M$2:$M$1071,"Fail") | F12: =COUNTIFS('Test Cases'!$B$2:$B$1071,A12,'Test Cases'!$M$2:$M$1071,"Blocked") | G12: =COUNTIFS('Test Cases'!$B$2:$B$1071,A12,'Test Cases'!$M$2:$M$1071,"N/A") | H12: =IFERROR((D12+E12)/(B12-G12),0) | I12: =IFERROR(D12/(D12+E12),0)
A13: Operations What-If | B13: =COUNTIF('Test Cases'!$B$2:$B$1071,A13) | C13: =COUNTIFS('Test Cases'!$B$2:$B$1071,A13,'Test Cases'!$M$2:$M$1071,"Not Run") | D13: =COUNTIFS('Test Cases'!$B$2:$B$1071,A13,'Test Cases'!$M$2:$M$1071,"Pass") | E13: =COUNTIFS('Test Cases'!$B$2:$B$1071,A13,'Test Cases'!$M$2:$M$1071,"Fail") | F13: =COUNTIFS('Test Cases'!$B$2:$B$1071,A13,'Test Cases'!$M$2:$M$1071,"Blocked") | G13: =COUNTIFS('Test Cases'!$B$2:$B$1071,A13,'Test Cases'!$M$2:$M$1071,"N/A") | H13: =IFERROR((D13+E13)/(B13-G13),0) | I13: =IFERROR(D13/(D13+E13),0)
... A27: End-to-end | B27: =COUNTIF('Test Cases'!$B$2:$B$1071,A27) | C27: =COUNTIFS('Test Cases'!$B$2:$B$1071,A27,'Test Cases'!$M$2:$M$1071,"Not Run") | D27: =COUNTIFS('Test Cases'!$B$2:$B$1071,A27,'Test Cases'!$M$2:$M$1071,"Pass") | E27: =COUNTIFS('Test Cases'!$B$2:$B$1071,A27,'Test Cases'!$M$2:$M$1071,"Fail") | F27: =COUNTIFS('Test Cases'!$B$2:$B$1071,A27,'Test Cases'!$M$2:$M$1071,"Blocked") | G27: =COUNTIFS('Test Cases'!$B$2:$B$1071,A27,'Test Cases'!$M$2:$M$1071,"N/A") | H27: =IFERROR((D27+E27)/(B27-G27),0) | I27: =IFERROR(D27/(D27+E27),0)
A28: Functional total | B28: 1070 | C28: =COUNTIF('Test Cases'!$M$2:$M$1071,"Not Run") | D28: =COUNTIF('Test Cases'!$M$2:$M$1071,"Pass") | E28: =COUNTIF('Test Cases'!$M$2:$M$1071,"Fail") | F28: =COUNTIF('Test Cases'!$M$2:$M$1071,"Blocked") | G28: =COUNTIF('Test Cases'!$M$2:$M$1071,"N/A") | H28: =IFERROR((D28+E28)/(B28-G28),0) | I28: =IFERROR(D28/(D28+E28),0)
A29: Source click checks | B29: 535 | C29: =COUNTIF('Click Checklist'!$K$2:$K$536,"Not Run") | D29: =COUNTIF('Click Checklist'!$K$2:$K$536,"Pass") | E29: =COUNTIF('Click Checklist'!$K$2:$K$536,"Fail") | F29: =COUNTIF('Click Checklist'!$K$2:$K$536,"Blocked") | G29: =COUNTIF('Click Checklist'!$K$2:$K$536,"N/A") | H29: =IFERROR((D29+E29)/(B29-G29),0) | I29: =IFERROR(D29/(D29+E29),0)

Sheet Smoke Test
A1: Order | B1: Test ID | C1: Module | D1: Scenario | E1: Status | F1: Actual Result | G1: Bug ID
A2: 1 | B2: AUTH-001 | C2: Login & Recovery | D2: Sign In — valid credentials and MFA | E2: Not Run
A3: 2 | B3: NAV-001 | C3: Navigation & Header | D3: Sidebar — Home | E3: Not Run
A4: 3 | B4: UPLOAD-006 | C4: Data Ingestion | D4: Upload POS CSV | E4: Not Run
A5: 4 | B5: HOME-003 | C5: Home | D5: KPI — revenue | E5: Not Run
A6: 5 | B6: CAFE-001 | C6: Cafe | D6: Revenue KPI — open | E6: Not Run
A7: 6 | B7: SVC-001 | C7: Services | D7: Revenue KPI — open | E7: Not Run
A8: 7 | B8: RETAIL-001 | C8: Retail | D8: Historical revenue KPI | E8: Not Run
A9: 8 | B9: INV-004 | C9: Inventory Monitor | D9: Refresh — normal | E9: Not Run
A10: 9 | B10: BUNDLE-016 | C10: Bundle Simulator | D10: Why this bundle? | E10: Not Run
A11: 10 | B11: PRICE-009 | C11: Pricing Laboratory | D11: Pricing discount slider | E11: Not Run
A12: 11 | B12: TRAFFIC-001 | C12: Traffic Optimizer | D12: Today (Live Shifts) | E12: Not Run
A13: 12 | B13: WHATIF-021 | C13: Operations What-If | D13: Start simulation — main | E13: Not Run
... A23: 22 | B23: E2E-007 | C23: End-to-end | D23: Owner secure access | E23: Not Run
